livecell_tracker/__init__.py
livecell_tracker/annotation/__init__.py
livecell_tracker/annotation/coco_utils.py
livecell_tracker/annotation/fiftyone_app.py
livecell_tracker/annotation/labelme2coco.py
livecell_tracker/core/__init__.py
livecell_tracker/core/single_cell.py
livecell_tracker/core/utils.py
livecell_tracker/preprocess/data_augmentation.py
livecell_tracker/segment/__init__.py
livecell_tracker/segment/datasets.py
livecell_tracker/segment/detectron_utils.py
livecell_tracker/segment/utils.py
livecell_tracker/track/__init__.py
livecell_tracker/track/movie.py
livecell_tracker/track/sort_tracker.py
livecell_tracker/track/sort_tracker_utils.py
livecell_tracker/trajectory/__init__.py
livecell_tracker/trajectory/constants.py
livecell_analyzer-0.0.0.dist-info/entry_points.txt
livecell_analyzer-0.0.0.dist-info/WHEEL
livecell_analyzer-0.0.0.dist-info/METADATA
livecell_analyzer-0.0.0.dist-info/RECORD
